Workbook

Sheet Mode d'emploi
B2: Comment utiliser ce classeur
B4: Les couleurs
B5: Jaune : à vous de remplir. Gris et gras : calculé automatiquement, n'y touchez pas.
B7: Onglet Courses
B8: Une ligne par course. Recopiez ce que vous recevez sur WhatsApp.
B9: Le prix HT et la TVA se déduisent seuls du prix TTC.
B10: Statut, Réglé, Type et Véhicule sont des listes déroulantes : cliquez sur la cellule.
B11: La ligne d'exemple est là pour montrer le format — écrasez-la.
B13: Onglet Clients
B14: Saisissez le nom exactement comme dans l'onglet Courses, sinon le rapprochement échoue.
B15: Nombre de courses, total dépensé, panier moyen et dernière course se calculent seuls.
B17: Onglet Chiffre d'affaires
... B29: emporter votre comptabilité.

Sheet Courses
A1: Registre des courses — As-mine
A2: Une ligne par course. Les colonnes jaunes se saisissent à la main ; les colonnes grises se calculent toutes seules.
A4: Référence | B4: Date course | C4: Heure | D4: Client | E4: Téléphone | F4: Départ | G4: Arrivée | H4: Type | I4: Véhicule | J4: Vol | K4: Chauffeur | L4: Prix TTC | M4: Prix HT | N4: TVA 10% | O4: Statut | P4: Réglé | Q4: N° facture | R4: Notes
A5: ASM-000001 | B5: 46254 | C5: 09:30 | D5: Marie Durand | E5: +33 6 11 22 33 44 | F5: 12 rue de la Paix, 75002 Paris | G5: Aéroport Roissy-CDG — Terminal 2E | H5: Forfait aéroport | I5: Berline | J5: AF1234 | K5: Kader B. | L5: 56 | M5: =IF(L5="","",L5/1.1) | N5: =IF(L5="","",L5-M5) | O5: Confirmée | P5: Oui | Q5: KADER-2026-0001 | R5: Exemple — remplacez cette ligne par votre première course
M6: =IF(L6="","",L6/1.1) | N6: =IF(L6="","",L6-M6)
M7: =IF(L7="","",L7/1.1) | N7: =IF(L7="","",L7-M7)
M8: =IF(L8="","",L8/1.1) | N8: =IF(L8="","",L8-M8)
M9: =IF(L9="","",L9/1.1) | N9: =IF(L9="","",L9-M9)
M10: =IF(L10="","",L10/1.1) | N10: =IF(L10="","",L10-M10)
M11: =IF(L11="","",L11/1.1) | N11: =IF(L11="","",L11-M11)
M12: =IF(L12="","",L12/1.1) | N12: =IF(L12="","",L12-M12)
M13: =IF(L13="","",L13/1.1) | N13: =IF(L13="","",L13-M13)
M14: =IF(L14="","",L14/1.1) | N14: =IF(L14="","",L14-M14)
M15: =IF(L15="","",L15/1.1) | N15: =IF(L15="","",L15-M15)
M16: =IF(L16="","",L16/1.1) | N16: =IF(L16="","",L16-M16)
M17: =IF(L17="","",L17/1.1) | N17: =IF(L17="","",L17-M17)
... M154: =IF(L154="","",L154/1.1) | N154: =IF(L154="","",L154-M154)

Sheet Clients
A1: Fichier clients
A2: Saisissez le nom et le téléphone ; le reste se calcule depuis l'onglet Courses.
A4: Client | B4: Téléphone | C4: Nb courses | D4: Total dépensé | E4: Panier moyen | F4: Dernière course | G4: Notes
A5: Marie Durand | B5: +33 6 11 22 33 44 | C5: =IF(A5="","",COUNTIF(Courses!$D$5:$D$154,A5)) | D5: =IF(A5="","",SUMIF(Courses!$D$5:$D$154,A5,Courses!$L$5:$L$154)) | E5: =IF(OR(A5="",C5=0),"",D5/C5) | F5: =IF(OR(A5="",C5=0),"",SUMPRODUCT(MAX((Courses!$D$5:$D$154=A5)*(Courses!$B$5:$B$154)))) | G5: Exemple — remplacez par votre premier client
C6: =IF(A6="","",COUNTIF(Courses!$D$5:$D$154,A6)) | D6: =IF(A6="","",SUMIF(Courses!$D$5:$D$154,A6,Courses!$L$5:$L$154)) | E6: =IF(OR(A6="",C6=0),"",D6/C6) | F6: =IF(OR(A6="",C6=0),"",SUMPRODUCT(MAX((Courses!$D$5:$D$154=A6)*(Courses!$B$5:$B$154))))
C7: =IF(A7="","",COUNTIF(Courses!$D$5:$D$154,A7)) | D7: =IF(A7="","",SUMIF(Courses!$D$5:$D$154,A7,Courses!$L$5:$L$154)) | E7: =IF(OR(A7="",C7=0),"",D7/C7) | F7: =IF(OR(A7="",C7=0),"",SUMPRODUCT(MAX((Courses!$D$5:$D$154=A7)*(Courses!$B$5:$B$154))))
C8: =IF(A8="","",COUNTIF(Courses!$D$5:$D$154,A8)) | D8: =IF(A8="","",SUMIF(Courses!$D$5:$D$154,A8,Courses!$L$5:$L$154)) | E8: =IF(OR(A8="",C8=0),"",D8/C8) | F8: =IF(OR(A8="",C8=0),"",SUMPRODUCT(MAX((Courses!$D$5:$D$154=A8)*(Courses!$B$5:$B$154))))
C9: =IF(A9="","",COUNTIF(Courses!$D$5:$D$154,A9)) | D9: =IF(A9="","",SUMIF(Courses!$D$5:$D$154,A9,Courses!$L$5:$L$154)) | E9: =IF(OR(A9="",C9=0),"",D9/C9) | F9: =IF(OR(A9="",C9=0),"",SUMPRODUCT(MAX((Courses!$D$5:$D$154=A9)*(Courses!$B$5:$B$154))))
C10: =IF(A10="","",COUNTIF(Courses!$D$5:$D$154,A10)) | D10: =IF(A10="","",SUMIF(Courses!$D$5:$D$154,A10,Courses!$L$5:$L$154)) | E10: =IF(OR(A10="",C10=0),"",D10/C10) | F10: =IF(OR(A10="",C10=0),"",SUMPRODUCT(MAX((Courses!$D$5:$D$154=A10)*(Courses!$B$5:$B$154))))
C11: =IF(A11="","",COUNTIF(Courses!$D$5:$D$154,A11)) | D11: =IF(A11="","",SUMIF(Courses!$D$5:$D$154,A11,Courses!$L$5:$L$154)) | E11: =IF(OR(A11="",C11=0),"",D11/C11) | F11: =IF(OR(A11="",C11=0),"",SUMPRODUCT(MAX((Courses!$D$5:$D$154=A11)*(Courses!$B$5:$B$154))))
C12: =IF(A12="","",COUNTIF(Courses!$D$5:$D$154,A12)) | D12: =IF(A12="","",SUMIF(Courses!$D$5:$D$154,A12,Courses!$L$5:$L$154)) | E12: =IF(OR(A12="",C12=0),"",D12/C12) | F12: =IF(OR(A12="",C12=0),"",SUMPRODUCT(MAX((Courses!$D$5:$D$154=A12)*(Courses!$B$5:$B$154))))
C13: =IF(A13="","",COUNTIF(Courses!$D$5:$D$154,A13)) | D13: =IF(A13="","",SUMIF(Courses!$D$5:$D$154,A13,Courses!$L$5:$L$154)) | E13: =IF(OR(A13="",C13=0),"",D13/C13) | F13: =IF(OR(A13="",C13=0),"",SUMPRODUCT(MAX((Courses!$D$5:$D$154=A13)*(Courses!$B$5:$B$154))))
C14: =IF(A14="","",COUNTIF(Courses!$D$5:$D$154,A14)) | D14: =IF(A14="","",SUMIF(Courses!$D$5:$D$154,A14,Courses!$L$5:$L$154)) | E14: =IF(OR(A14="",C14=0),"",D14/C14) | F14: =IF(OR(A14="",C14=0),"",SUMPRODUCT(MAX((Courses!$D$5:$D$154=A14)*(Courses!$B$5:$B$154))))
C15: =IF(A15="","",COUNTIF(Courses!$D$5:$D$154,A15)) | D15: =IF(A15="","",SUMIF(Courses!$D$5:$D$154,A15,Courses!$L$5:$L$154)) | E15: =IF(OR(A15="",C15=0),"",D15/C15) | F15: =IF(OR(A15="",C15=0),"",SUMPRODUCT(MAX((Courses!$D$5:$D$154=A15)*(Courses!$B$5:$B$154))))
C16: =IF(A16="","",COUNTIF(Courses!$D$5:$D$154,A16)) | D16: =IF(A16="","",SUMIF(Courses!$D$5:$D$154,A16,Courses!$L$5:$L$154)) | E16: =IF(OR(A16="",C16=0),"",D16/C16) | F16: =IF(OR(A16="",C16=0),"",SUMPRODUCT(MAX((Courses!$D$5:$D$154=A16)*(Courses!$B$5:$B$154))))
C17: =IF(A17="","",COUNTIF(Courses!$D$5:$D$154,A17)) | D17: =IF(A17="","",SUMIF(Courses!$D$5:$D$154,A17,Courses!$L$5:$L$154)) | E17: =IF(OR(A17="",C17=0),"",D17/C17) | F17: =IF(OR(A17="",C17=0),"",SUMPRODUCT(MAX((Courses!$D$5:$D$154=A17)*(Courses!$B$5:$B$154))))
... C64: =IF(A64="","",COUNTIF(Courses!$D$5:$D$154,A64)) | D64: =IF(A64="","",SUMIF(Courses!$D$5:$D$154,A64,Courses!$L$5:$L$154)) | E64: =IF(OR(A64="",C64=0),"",D64/C64) | F64: =IF(OR(A64="",C64=0),"",SUMPRODUCT(MAX((Courses!$D$5:$D$154=A64)*(Courses!$B$5:$B$154))))

Sheet Chiffre d'affaires
A1: Chiffre d'affaires par mois
A2: Tout se calcule depuis l'onglet Courses. Aucune saisie ici.
A4: Année | B4: 2026 | C4: ← année étudiée, modifiable
A6: Mois | B6: Courses | C6: CA TTC | D6: CA HT | E6: TVA due | F6: Panier moyen | G6: Encaissé | H6: Reste à encaisser
A7: Janvier | B7: =SUMPRODUCT((YEAR(Courses!$B$5:$B$154)=$B$4)*(MONTH(Courses!$B$5:$B$154)=1)*(Courses!$O$5:$O$154<>"Annulée")*(Courses!$B$5:$B$154<>"")*1) | C7: =SUMPRODUCT((YEAR(Courses!$B$5:$B$154)=$B$4)*(MONTH(Courses!$B$5:$B$154)=1)*(Courses!$O$5:$O$154<>"Annulée")*(Courses!$B$5:$B$154<>"")*Courses!$L$5:$L$154) | D7: =C7/1.1 | E7: =C7-D7 | F7: =IF(B7=0,0,C7/B7) | G7: =SUMPRODUCT((YEAR(Courses!$B$5:$B$154)=$B$4)*(MONTH(Courses!$B$5:$B$154)=1)*(Courses!$O$5:$O$154<>"Annulée")*(Courses!$B$5:$B$154<>"")*(Courses!$P$5:$P$154="Oui")*Courses!$L$5:$L$154) | H7: =C7-G7
A8: Février | B8: =SUMPRODUCT((YEAR(Courses!$B$5:$B$154)=$B$4)*(MONTH(Courses!$B$5:$B$154)=2)*(Courses!$O$5:$O$154<>"Annulée")*(Courses!$B$5:$B$154<>"")*1) | C8: =SUMPRODUCT((YEAR(Courses!$B$5:$B$154)=$B$4)*(MONTH(Courses!$B$5:$B$154)=2)*(Courses!$O$5:$O$154<>"Annulée")*(Courses!$B$5:$B$154<>"")*Courses!$L$5:$L$154) | D8: =C8/1.1 | E8: =C8-D8 | F8: =IF(B8=0,0,C8/B8) | G8: =SUMPRODUCT((YEAR(Courses!$B$5:$B$154)=$B$4)*(MONTH(Courses!$B$5:$B$154)=2)*(Courses!$O$5:$O$154<>"Annulée")*(Courses!$B$5:$B$154<>"")*(Courses!$P$5:$P$154="Oui")*Courses!$L$5:$L$154) | H8: =C8-G8
A9: Mars | B9: =SUMPRODUCT((YEAR(Courses!$B$5:$B$154)=$B$4)*(MONTH(Courses!$B$5:$B$154)=3)*(Courses!$O$5:$O$154<>"Annulée")*(Courses!$B$5:$B$154<>"")*1) | C9: =SUMPRODUCT((YEAR(Courses!$B$5:$B$154)=$B$4)*(MONTH(Courses!$B$5:$B$154)=3)*(Courses!$O$5:$O$154<>"Annulée")*(Courses!$B$5:$B$154<>"")*Courses!$L$5:$L$154) | D9: =C9/1.1 | E9: =C9-D9 | F9: =IF(B9=0,0,C9/B9) | G9: =SUMPRODUCT((YEAR(Courses!$B$5:$B$154)=$B$4)*(MONTH(Courses!$B$5:$B$154)=3)*(Courses!$O$5:$O$154<>"Annulée")*(Courses!$B$5:$B$154<>"")*(Courses!$P$5:$P$154="Oui")*Courses!$L$5:$L$154) | H9: =C9-G9
A10: Avril | B10: =SUMPRODUCT((YEAR(Courses!$B$5:$B$154)=$B$4)*(MONTH(Courses!$B$5:$B$154)=4)*(Courses!$O$5:$O$154<>"Annulée")*(Courses!$B$5:$B$154<>"")*1) | C10: =SUMPRODUCT((YEAR(Courses!$B$5:$B$154)=$B$4)*(MONTH(Courses!$B$5:$B$154)=4)*(Courses!$O$5:$O$154<>"Annulée")*(Courses!$B$5:$B$154<>"")*Courses!$L$5:$L$154) | D10: =C10/1.1 | E10: =C10-D10 | F10: =IF(B10=0,0,C10/B10) | G10: =SUMPRODUCT((YEAR(Courses!$B$5:$B$154)=$B$4)*(MONTH(Courses!$B$5:$B$154)=4)*(Courses!$O$5:$O$154<>"Annulée")*(Courses!$B$5:$B$154<>"")*(Courses!$P$5:$P$154="Oui")*Courses!$L$5:$L$154) | H10: =C10-G10
A11: Mai | B11: =SUMPRODUCT((YEAR(Courses!$B$5:$B$154)=$B$4)*(MONTH(Courses!$B$5:$B$154)=5)*(Courses!$O$5:$O$154<>"Annulée")*(Courses!$B$5:$B$154<>"")*1) | C11: =SUMPRODUCT((YEAR(Courses!$B$5:$B$154)=$B$4)*(MONTH(Courses!$B$5:$B$154)=5)*(Courses!$O$5:$O$154<>"Annulée")*(Courses!$B$5:$B$154<>"")*Courses!$L$5:$L$154) | D11: =C11/1.1 | E11: =C11-D11 | F11: =IF(B11=0,0,C11/B11) | G11: =SUMPRODUCT((YEAR(Courses!$B$5:$B$154)=$B$4)*(MONTH(Courses!$B$5:$B$154)=5)*(Courses!$O$5:$O$154<>"Annulée")*(Courses!$B$5:$B$154<>"")*(Courses!$P$5:$P$154="Oui")*Courses!$L$5:$L$154) | H11: =C11-G11
A12: Juin | B12: =SUMPRODUCT((YEAR(Courses!$B$5:$B$154)=$B$4)*(MONTH(Courses!$B$5:$B$154)=6)*(Courses!$O$5:$O$154<>"Annulée")*(Courses!$B$5:$B$154<>"")*1) | C12: =SUMPRODUCT((YEAR(Courses!$B$5:$B$154)=$B$4)*(MONTH(Courses!$B$5:$B$154)=6)*(Courses!$O$5:$O$154<>"Annulée")*(Courses!$B$5:$B$154<>"")*Courses!$L$5:$L$154) | D12: =C12/1.1 | E12: =C12-D12 | F12: =IF(B12=0,0,C12/B12) | G12: =SUMPRODUCT((YEAR(Courses!$B$5:$B$154)=$B$4)*(MONTH(Courses!$B$5:$B$154)=6)*(Courses!$O$5:$O$154<>"Annulée")*(Courses!$B$5:$B$154<>"")*(Courses!$P$5:$P$154="Oui")*Courses!$L$5:$L$154) | H12: =C12-G12
A13: Juillet | B13: =SUMPRODUCT((YEAR(Courses!$B$5:$B$154)=$B$4)*(MONTH(Courses!$B$5:$B$154)=7)*(Courses!$O$5:$O$154<>"Annulée")*(Courses!$B$5:$B$154<>"")*1) | C13: =SUMPRODUCT((YEAR(Courses!$B$5:$B$154)=$B$4)*(MONTH(Courses!$B$5:$B$154)=7)*(Courses!$O$5:$O$154<>"Annulée")*(Courses!$B$5:$B$154<>"")*Courses!$L$5:$L$154) | D13: =C13/1.1 | E13: =C13-D13 | F13: =IF(B13=0,0,C13/B13) | G13: =SUMPRODUCT((YEAR(Courses!$B$5:$B$154)=$B$4)*(MONTH(Courses!$B$5:$B$154)=7)*(Courses!$O$5:$O$154<>"Annulée")*(Courses!$B$5:$B$154<>"")*(Courses!$P$5:$P$154="Oui")*Courses!$L$5:$L$154) | H13: =C13-G13
A14: Août | B14: =SUMPRODUCT((YEAR(Courses!$B$5:$B$154)=$B$4)*(MONTH(Courses!$B$5:$B$154)=8)*(Courses!$O$5:$O$154<>"Annulée")*(Courses!$B$5:$B$154<>"")*1) | C14: =SUMPRODUCT((YEAR(Courses!$B$5:$B$154)=$B$4)*(MONTH(Courses!$B$5:$B$154)=8)*(Courses!$O$5:$O$154<>"Annulée")*(Courses!$B$5:$B$154<>"")*Courses!$L$5:$L$154) | D14: =C14/1.1 | E14: =C14-D14 | F14: =IF(B14=0,0,C14/B14) | G14: =SUMPRODUCT((YEAR(Courses!$B$5:$B$154)=$B$4)*(MONTH(Courses!$B$5:$B$154)=8)*(Courses!$O$5:$O$154<>"Annulée")*(Courses!$B$5:$B$154<>"")*(Courses!$P$5:$P$154="Oui")*Courses!$L$5:$L$154) | H14: =C14-G14
A15: Septembre | B15: =SUMPRODUCT((YEAR(Courses!$B$5:$B$154)=$B$4)*(MONTH(Courses!$B$5:$B$154)=9)*(Courses!$O$5:$O$154<>"Annulée")*(Courses!$B$5:$B$154<>"")*1) | C15: =SUMPRODUCT((YEAR(Courses!$B$5:$B$154)=$B$4)*(MONTH(Courses!$B$5:$B$154)=9)*(Courses!$O$5:$O$154<>"Annulée")*(Courses!$B$5:$B$154<>"")*Courses!$L$5:$L$154) | D15: =C15/1.1 | E15: =C15-D15 | F15: =IF(B15=0,0,C15/B15) | G15: =SUMPRODUCT((YEAR(Courses!$B$5:$B$154)=$B$4)*(MONTH(Courses!$B$5:$B$154)=9)*(Courses!$O$5:$O$154<>"Annulée")*(Courses!$B$5:$B$154<>"")*(Courses!$P$5:$P$154="Oui")*Courses!$L$5:$L$154) | H15: =C15-G15
A16: Octobre | B16: =SUMPRODUCT((YEAR(Courses!$B$5:$B$154)=$B$4)*(MONTH(Courses!$B$5:$B$154)=10)*(Courses!$O$5:$O$154<>"Annulée")*(Courses!$B$5:$B$154<>"")*1) | C16: =SUMPRODUCT((YEAR(Courses!$B$5:$B$154)=$B$4)*(MONTH(Courses!$B$5:$B$154)=10)*(Courses!$O$5:$O$154<>"Annulée")*(Courses!$B$5:$B$154<>"")*Courses!$L$5:$L$154) | D16: =C16/1.1 | E16: =C16-D16 | F16: =IF(B16=0,0,C16/B16) | G16: =SUMPRODUCT((YEAR(Courses!$B$5:$B$154)=$B$4)*(MONTH(Courses!$B$5:$B$154)=10)*(Courses!$O$5:$O$154<>"Annulée")*(Courses!$B$5:$B$154<>"")*(Courses!$P$5:$P$154="Oui")*Courses!$L$5:$L$154) | H16: =C16-G16
A17: Novembre | B17: =SUMPRODUCT((YEAR(Courses!$B$5:$B$154)=$B$4)*(MONTH(Courses!$B$5:$B$154)=11)*(Courses!$O$5:$O$154<>"Annulée")*(Courses!$B$5:$B$154<>"")*1) | C17: =SUMPRODUCT((YEAR(Courses!$B$5:$B$154)=$B$4)*(MONTH(Courses!$B$5:$B$154)=11)*(Courses!$O$5:$O$154<>"Annulée")*(Courses!$B$5:$B$154<>"")*Courses!$L$5:$L$154) | D17: =C17/1.1 | E17: =C17-D17 | F17: =IF(B17=0,0,C17/B17) | G17: =SUMPRODUCT((YEAR(Courses!$B$5:$B$154)=$B$4)*(MONTH(Courses!$B$5:$B$154)=11)*(Courses!$O$5:$O$154<>"Annulée")*(Courses!$B$5:$B$154<>"")*(Courses!$P$5:$P$154="Oui")*Courses!$L$5:$L$154) | H17: =C17-G17
A18: Décembre | B18: =SUMPRODUCT((YEAR(Courses!$B$5:$B$154)=$B$4)*(MONTH(Courses!$B$5:$B$154)=12)*(Courses!$O$5:$O$154<>"Annulée")*(Courses!$B$5:$B$154<>"")*1) | C18: =SUMPRODUCT((YEAR(Courses!$B$5:$B$154)=$B$4)*(MONTH(Courses!$B$5:$B$154)=12)*(Courses!$O$5:$O$154<>"Annulée")*(Courses!$B$5:$B$154<>"")*Courses!$L$5:$L$154) | D18: =C18/1.1 | E18: =C18-D18 | F18: =IF(B18=0,0,C18/B18) | G18: =SUMPRODUCT((YEAR(Courses!$B$5:$B$154)=$B$4)*(MONTH(Courses!$B$5:$B$154)=12)*(Courses!$O$5:$O$154<>"Annulée")*(Courses!$B$5:$B$154<>"")*(Courses!$P$5:$P$154="Oui")*Courses!$L$5:$L$154) | H18: =C18-G18
A19: TOTAL | B19: =SUM(B7:B18) | C19: =SUM(C7:C18) | D19: =SUM(D7:D18) | E19: =SUM(E7:E18) | F19: =IF(B19=0,0,C19/B19) | G19: =SUM(G7:G18) | H19: =SUM(H7:H18)
A21: TVA due : 10 % applicable au transport de personnes. Les courses au statut « Annulée » sont exclues du chiffre d'affaires.
